<?xml version="1.0" encoding="utf-8" ?>
<dwsync>
<file name="404.php" server="maurinadavis.com/public_html/CabotCruise/" local="131853465000000000" remote="131853465000000000" Dst="1" />
<file name="archive.php" server="maurinadavis.com/public_html/CabotCruise/" local="131893489800000000" remote="131893489800000000" Dst="1" />
<file name="comments.php" server="maurinadavis.com/public_html/CabotCruise/" local="131893495200000000" remote="131893495200000000" Dst="1" />
<file name="footer.php" server="maurinadavis.com/public_html/CabotCruise/" local="131865420000000000" remote="131865420000000000" Dst="1" />
<file name="functions.php" server="maurinadavis.com/public_html/CabotCruise/" local="131913636000000000" remote="131913636000000000" Dst="1" />
<file name="header.php" server="maurinadavis.com/public_html/CabotCruise/" local="131893495200000000" remote="131893495200000000" Dst="1" />
<file name="image.php" server="maurinadavis.com/public_html/CabotCruise/" local="131893489800000000" remote="131893489800000000" Dst="1" />
<file name="index.php" server="maurinadavis.com/public_html/CabotCruise/" local="131893489800000000" remote="131893489800000000" Dst="1" />
<file name="package-lock.json" server="maurinadavis.com/public_html/CabotCruise/" local="131880945600000000" remote="131880945600000000" Dst="1" />
<file name="package.json" server="maurinadavis.com/public_html/CabotCruise/" local="131880945600000000" remote="131880945600000000" Dst="1" />
<file name="page.php" server="maurinadavis.com/public_html/CabotCruise/" local="131853465000000000" remote="131853465000000000" Dst="1" />
<file name="postcss.config.js" server="maurinadavis.com/public_html/CabotCruise/" local="131865420000000000" remote="131865420000000000" Dst="1" />
<file name="print.css" server="maurinadavis.com/public_html/CabotCruise/" local="131871400200000000" remote="131871400200000000" Dst="1" />
<file name="print.scss" server="maurinadavis.com/public_html/CabotCruise/" local="131871400200000000" remote="131871400200000000" Dst="1" />
<file name="readme.txt" server="maurinadavis.com/public_html/CabotCruise/" local="131913648600000000" remote="131913648600000000" Dst="1" />
<file name="screenshot.png" server="maurinadavis.com/public_html/CabotCruise/" local="131883742200000000" remote="131883742200000000" Dst="1" />
<file name="search.php" server="maurinadavis.com/public_html/CabotCruise/" local="131865420000000000" remote="131865420000000000" Dst="1" />
<file name="single.php" server="maurinadavis.com/public_html/CabotCruise/" local="131893493400000000" remote="131893493400000000" Dst="1" />
<file name="style-editor-customizer.css" server="maurinadavis.com/public_html/CabotCruise/" local="131948911800000000" remote="131948911800000000" Dst="1" />
<file name="style-editor-customizer.scss" server="maurinadavis.com/public_html/CabotCruise/" local="131865420000000000" remote="131865420000000000" Dst="1" />
<file name="style-editor.css" server="maurinadavis.com/public_html/CabotCruise/" local="131893496400000000" remote="131893496400000000" Dst="1" />
<file name="style-editor.scss" server="maurinadavis.com/public_html/CabotCruise/" local="131893496400000000" remote="131893496400000000" Dst="1" />
<file name="style-rtl.css" server="maurinadavis.com/public_html/CabotCruise/" local="131913648600000000" remote="131913648600000000" Dst="1" />
<file name="style.css" server="maurinadavis.com/public_html/CabotCruise/" local="131913648600000000" remote="131913648600000000" Dst="1" />
<file name="style.scss" server="maurinadavis.com/public_html/CabotCruise/" local="131913648600000000" remote="131913648600000000" Dst="1" />
</dwsync>