<?xml version="1.0" encoding="utf-8" ?>
<dwsync>
<file name="404.php" server="maurinadavis.com/public_html/CabotCruise/" local="131213376000000000" remote="131213376000000000" Dst="1" />
<file name="archive.php" server="maurinadavis.com/public_html/CabotCruise/" local="131224608000000000" remote="131224608000000000" Dst="1" />
<file name="comments.php" server="maurinadavis.com/public_html/CabotCruise/" local="131263452000000000" remote="131263452000000000" Dst="1" />
<file name="footer.php" server="maurinadavis.com/public_html/CabotCruise/" local="131369760000000000" remote="131369760000000000" Dst="1" />
<file name="front-page.php" server="maurinadavis.com/public_html/CabotCruise/" local="131602140000000000" remote="131602140000000000" Dst="1" />
<file name="functions.php" server="maurinadavis.com/public_html/CabotCruise/" local="131913636000000000" remote="131913636000000000" Dst="1" />
<file name="header.php" server="maurinadavis.com/public_html/CabotCruise/" local="131266908000000000" remote="131266908000000000" Dst="1" />
<file name="index.php" server="maurinadavis.com/public_html/CabotCruise/" local="131224608000000000" remote="131224608000000000" Dst="1" />
<file name="page.php" server="maurinadavis.com/public_html/CabotCruise/" local="131216832000000000" remote="131216832000000000" Dst="1" />
<file name="README.txt" server="maurinadavis.com/public_html/CabotCruise/" local="131913648600000000" remote="131913648600000000" Dst="1" />
<file name="rtl.css" server="maurinadavis.com/public_html/CabotCruise/" local="131697216000000000" remote="131697216000000000" Dst="1" />
<file name="screenshot.png" server="maurinadavis.com/public_html/CabotCruise/" local="131213376000000000" remote="131213376000000000" Dst="1" />
<file name="search.php" server="maurinadavis.com/public_html/CabotCruise/" local="131224608000000000" remote="131224608000000000" Dst="1" />
<file name="searchform.php" server="maurinadavis.com/public_html/CabotCruise/" local="131912831400000000" remote="131912831400000000" Dst="1" />
<file name="sidebar.php" server="maurinadavis.com/public_html/CabotCruise/" local="131514048000000000" remote="131514048000000000" Dst="1" />
<file name="single.php" server="maurinadavis.com/public_html/CabotCruise/" local="131263452000000000" remote="131263452000000000" Dst="1" />
<file name="style.css" server="maurinadavis.com/public_html/CabotCruise/" local="131913648600000000" remote="131913648600000000" Dst="1" />
</dwsync>